gala/io.py
gala/cconfig.pyx
gala/_astropy_init.py
gala/setup_package.py
gala/_compiler.c
gala/extra_compile_macros.h
gala/__init__.py
gala/units.py
gala/_cconfig.cpython-37m-x86_64-linux-gnu.so
gala/conftest.py
gala/compiler_version.cpython-37m-x86_64-linux-gnu.so
gala/version.py
gala/cconfig.c
gala/mpl_style.py
gala/util.py
gala/dynamics/nonlinear.py
gala/dynamics/orbit.py
gala/dynamics/core.py
gala/dynamics/setup_package.py
gala/dynamics/__init__.py
gala/dynamics/representation_nd.py
gala/dynamics/actionangle.py
gala/dynamics/plot.py
gala/dynamics/analyticactionangle.py
gala/dynamics/util.py
gala/dynamics/_genfunc/visualize_surfaces.py
gala/dynamics/_genfunc/test_potentials.py
gala/dynamics/_genfunc/__init__.py
gala/dynamics/_genfunc/toy_potentials.py
gala/dynamics/_genfunc/genfunc_3d.py
gala/dynamics/_genfunc/solver.py
gala/dynamics/lyapunov/dop853_lyapunov.cpython-37m-x86_64-linux-gnu.so
gala/dynamics/lyapunov/dop853_lyapunov.pyx
gala/dynamics/lyapunov/__init__.py
gala/dynamics/lyapunov/dop853_lyapunov.c
gala/dynamics/nbody/nbody_helper.h
gala/dynamics/nbody/nbody.pyx
gala/dynamics/nbody/nbody.pxd
gala/dynamics/nbody/core.py
gala/dynamics/nbody/nbody.cpython-37m-x86_64-linux-gnu.so
gala/dynamics/nbody/__init__.py
gala/dynamics/nbody/nbody.c
gala/dynamics/nbody/tests/__init__.py
gala/dynamics/nbody/tests/test_nbody.py
gala/dynamics/mockstream/mockstream.pyx
gala/dynamics/mockstream/_coord.cpython-37m-x86_64-linux-gnu.so
gala/dynamics/mockstream/core.py
gala/dynamics/mockstream/df.c
gala/dynamics/mockstream/mockstream.c
gala/dynamics/mockstream/df.cpython-37m-x86_64-linux-gnu.so
gala/dynamics/mockstream/__init__.py
gala/dynamics/mockstream/df.pyx
gala/dynamics/mockstream/_coord.pxd
gala/dynamics/mockstream/_coord.pyx
gala/dynamics/mockstream/df.pxd
gala/dynamics/mockstream/mockstream_generator.py
gala/dynamics/mockstream/_coord.c
gala/dynamics/mockstream/_mockstream.cpython-37m-x86_64-linux-gnu.so
astro_gala-1.2.dist-info/RECORD
astro_gala-1.2.dist-info/WHEEL
astro_gala-1.2.dist-info/METADATA
astro_gala-1.2.dist-info/top_level.txt
astro_gala-1.2.dist-info/LICENSE
