Metadata-Version: 2.1
Name: astro-gala
Version: 1.2
Summary: Galactic dynamics in Python
Home-page: http://gala.adrian.pw/
Author: Adrian M. Price-Whelan
Author-email: adrianmpw@gmail.com
License: MIT
Platform: UNKNOWN
Requires-Python: >=3.6
Provides-Extra: all
Provides-Extra: test
Provides-Extra: docs
